[{"model": "admin.logentry", "pk": 1, "fields": {"action_time": "2023-07-26T08:57:34.685Z", "user": 1, "content_type": 7, "object_id": "1", "object_repr": "└ъЄЁшё√", "action_flag": 1, "change_message": "[{\"added\": {}}]"}}, {"model": "admin.logentry", "pk": 2, "fields": {"action_time": "2023-07-26T08:57:46.365Z", "user": 1, "content_type": 7, "object_id": "2", "object_repr": "╧хтшЎ√", "action_flag": 1, "change_message": "[{\"added\": {}}]"}}, {"model": "admin.logentry", "pk": 3, "fields": {"action_time": "2023-07-26T10:13:53.797Z", "user": 1, "content_type": 8, "object_id": "1", "object_repr": "╙ьр ╥єЁьрэ", "action_flag": 1, "change_message": "[{\"added\": {}}]"}}, {"model": "admin.logentry", "pk": 4, "fields": {"action_time": "2023-07-26T10:15:18.785Z", "user": 1, "content_type": 8, "object_id": "2", "object_repr": "╠рЁую ╨юссш", "action_flag": 1, "change_message": "[{\"added\": {}}]"}}, {"model": "admin.logentry", "pk": 5, "fields": {"action_time": "2023-07-26T10:16:29.648Z", "user": 1, "content_type": 8, "object_id": "3", "object_repr": "└эфцхышэр ─цюыш", "action_flag": 1, "change_message": "[{\"added\": {}}]"}}, {"model": "admin.logentry", "pk": 6, "fields": {"action_time": "2023-07-26T10:17:26.871Z", "user": 1, "content_type": 8, "object_id": "4", "object_repr": "─цхээшЇхЁ ╦юєЁхэё", "action_flag": 1, "change_message": "[{\"added\": {}}]"}}, {"model": "admin.logentry", "pk": 7, "fields": {"action_time": "2023-07-26T10:18:09.211Z", "user": 1, "content_type": 8, "object_id": "5", "object_repr": "─цєыш  ╨юсхЁЄё", "action_flag": 1, "change_message": "[{\"added\": {}}]"}}, {"model": "admin.logentry", "pk": 8, "fields": {"action_time": "2023-07-26T10:18:58.020Z", "user": 1, "content_type": 8, "object_id": "6", "object_repr": "└Ёшрэр ├Ёрэфх", "action_flag": 1, "change_message": "[{\"added\": {}}]"}}, {"model": "admin.logentry", "pk": 9, "fields": {"action_time": "2023-07-26T10:19:54.183Z", "user": 1, "content_type": 8, "object_id": "7", "object_repr": "┴хщюэёх", "action_flag": 1, "change_message": "[{\"added\": {}}]"}}, {"model": "admin.logentry", "pk": 10, "fields": {"action_time": "2023-07-26T10:21:15.213Z", "user": 1, "content_type": 8, "object_id": "8", "object_repr": "╩¤ЄЄш ╧хЁЁш", "action_flag": 1, "change_message": "[{\"added\": {}}]"}}, {"model": "admin.logentry", "pk": 11, "fields": {"action_time": "2023-07-26T10:22:02.320Z", "user": 1, "content_type": 8, "object_id": "9", "object_repr": "╨шрээр", "action_flag": 1, "change_message": "[{\"added\": {}}]"}}, {"model": "admin.logentry", "pk": 12, "fields": {"action_time": "2023-07-26T10:22:37.702Z", "user": 1, "content_type": 8, "object_id": "10", "object_repr": "╪ръшЁр", "action_flag": 1, "change_message": "[{\"added\": {}}]"}}, {"model": "admin.logentry", "pk": 13, "fields": {"action_time": "2023-07-27T15:42:40.794Z", "user": 1, "content_type": 8, "object_id": "2", "object_repr": "╠рЁую ╨юссш", "action_flag": 2, "change_message": "[{\"changed\": {\"fields\": [\"\\u041f\\u0443\\u0431\\u043b\\u0438\\u043a\\u0430\\u0446\\u0438\\u044f\"]}}]"}}, {"model": "admin.logentry", "pk": 14, "fields": {"action_time": "2023-07-27T15:42:40.795Z", "user": 1, "content_type": 8, "object_id": "3", "object_repr": "└эфцхышэр ─цюыш", "action_flag": 2, "change_message": "[{\"changed\": {\"fields\": [\"\\u041f\\u0443\\u0431\\u043b\\u0438\\u043a\\u0430\\u0446\\u0438\\u044f\"]}}]"}}, {"model": "admin.logentry", "pk": 15, "fields": {"action_time": "2023-07-27T15:42:40.797Z", "user": 1, "content_type": 8, "object_id": "4", "object_repr": "─цхээшЇхЁ ╦юєЁхэё", "action_flag": 2, "change_message": "[{\"changed\": {\"fields\": [\"\\u041f\\u0443\\u0431\\u043b\\u0438\\u043a\\u0430\\u0446\\u0438\\u044f\"]}}]"}}, {"model": "admin.logentry", "pk": 16, "fields": {"action_time": "2023-07-27T15:42:40.798Z", "user": 1, "content_type": 8, "object_id": "5", "object_repr": "─цєыш  ╨юсхЁЄё", "action_flag": 2, "change_message": "[{\"changed\": {\"fields\": [\"\\u041f\\u0443\\u0431\\u043b\\u0438\\u043a\\u0430\\u0446\\u0438\\u044f\"]}}]"}}, {"model": "admin.logentry", "pk": 17, "fields": {"action_time": "2023-07-27T15:42:40.799Z", "user": 1, "content_type": 8, "object_id": "6", "object_repr": "└Ёшрэр ├Ёрэфх", "action_flag": 2, "change_message": "[{\"changed\": {\"fields\": [\"\\u041f\\u0443\\u0431\\u043b\\u0438\\u043a\\u0430\\u0446\\u0438\\u044f\"]}}]"}}, {"model": "admin.logentry", "pk": 18, "fields": {"action_time": "2023-07-27T15:42:40.800Z", "user": 1, "content_type": 8, "object_id": "7", "object_repr": "┴хщюэёх", "action_flag": 2, "change_message": "[{\"changed\": {\"fields\": [\"\\u041f\\u0443\\u0431\\u043b\\u0438\\u043a\\u0430\\u0446\\u0438\\u044f\"]}}]"}}, {"model": "admin.logentry", "pk": 19, "fields": {"action_time": "2023-07-27T15:42:40.802Z", "user": 1, "content_type": 8, "object_id": "8", "object_repr": "╩¤ЄЄш ╧хЁЁш", "action_flag": 2, "change_message": "[{\"changed\": {\"fields\": [\"\\u041f\\u0443\\u0431\\u043b\\u0438\\u043a\\u0430\\u0446\\u0438\\u044f\"]}}]"}}, {"model": "admin.logentry", "pk": 20, "fields": {"action_time": "2023-07-27T15:42:40.804Z", "user": 1, "content_type": 8, "object_id": "9", "object_repr": "╨шрээр", "action_flag": 2, "change_message": "[{\"changed\": {\"fields\": [\"\\u041f\\u0443\\u0431\\u043b\\u0438\\u043a\\u0430\\u0446\\u0438\\u044f\"]}}]"}}, {"model": "admin.logentry", "pk": 21, "fields": {"action_time": "2023-07-27T15:42:40.805Z", "user": 1, "content_type": 8, "object_id": "10", "object_repr": "╪ръшЁр", "action_flag": 2, "change_message": "[{\"changed\": {\"fields\": [\"\\u041f\\u0443\\u0431\\u043b\\u0438\\u043a\\u0430\\u0446\\u0438\\u044f\"]}}]"}}, {"model": "admin.logentry", "pk": 22, "fields": {"action_time": "2023-07-27T15:42:40.806Z", "user": 1, "content_type": 8, "object_id": "11", "object_repr": "└эрёЄрёш  ▌°ыш", "action_flag": 2, "change_message": "[{\"changed\": {\"fields\": [\"\\u041f\\u0443\\u0431\\u043b\\u0438\\u043a\\u0430\\u0446\\u0438\\u044f\"]}}]"}}, {"model": "admin.logentry", "pk": 23, "fields": {"action_time": "2023-07-27T15:42:58.523Z", "user": 1, "content_type": 8, "object_id": "2", "object_repr": "╠рЁую ╨юссш", "action_flag": 2, "change_message": "[{\"changed\": {\"fields\": [\"\\u041f\\u0443\\u0431\\u043b\\u0438\\u043a\\u0430\\u0446\\u0438\\u044f\"]}}]"}}, {"model": "admin.logentry", "pk": 24, "fields": {"action_time": "2023-07-27T15:42:58.525Z", "user": 1, "content_type": 8, "object_id": "3", "object_repr": "└эфцхышэр ─цюыш", "action_flag": 2, "change_message": "[{\"changed\": {\"fields\": [\"\\u041f\\u0443\\u0431\\u043b\\u0438\\u043a\\u0430\\u0446\\u0438\\u044f\"]}}]"}}, {"model": "admin.logentry", "pk": 25, "fields": {"action_time": "2023-07-27T15:42:58.526Z", "user": 1, "content_type": 8, "object_id": "4", "object_repr": "─цхээшЇхЁ ╦юєЁхэё", "action_flag": 2, "change_message": "[{\"changed\": {\"fields\": [\"\\u041f\\u0443\\u0431\\u043b\\u0438\\u043a\\u0430\\u0446\\u0438\\u044f\"]}}]"}}, {"model": "admin.logentry", "pk": 26, "fields": {"action_time": "2023-07-27T15:42:58.527Z", "user": 1, "content_type": 8, "object_id": "5", "object_repr": "─цєыш  ╨юсхЁЄё", "action_flag": 2, "change_message": "[{\"changed\": {\"fields\": [\"\\u041f\\u0443\\u0431\\u043b\\u0438\\u043a\\u0430\\u0446\\u0438\\u044f\"]}}]"}}, {"model": "admin.logentry", "pk": 27, "fields": {"action_time": "2023-07-27T15:42:58.528Z", "user": 1, "content_type": 8, "object_id": "6", "object_repr": "└Ёшрэр ├Ёрэфх", "action_flag": 2, "change_message": "[{\"changed\": {\"fields\": [\"\\u041f\\u0443\\u0431\\u043b\\u0438\\u043a\\u0430\\u0446\\u0438\\u044f\"]}}]"}}, {"model": "admin.logentry", "pk": 28, "fields": {"action_time": "2023-07-27T15:42:58.530Z", "user": 1, "content_type": 8, "object_id": "7", "object_repr": "┴хщюэёх", "action_flag": 2, "change_message": "[{\"changed\": {\"fields\": [\"\\u041f\\u0443\\u0431\\u043b\\u0438\\u043a\\u0430\\u0446\\u0438\\u044f\"]}}]"}}, {"model": "admin.logentry", "pk": 29, "fields": {"action_time": "2023-07-27T15:42:58.531Z", "user": 1, "content_type": 8, "object_id": "8", "object_repr": "╩¤ЄЄш ╧хЁЁш", "action_flag": 2, "change_message": "[{\"changed\": {\"fields\": [\"\\u041f\\u0443\\u0431\\u043b\\u0438\\u043a\\u0430\\u0446\\u0438\\u044f\"]}}]"}}, {"model": "admin.logentry", "pk": 30, "fields": {"action_time": "2023-07-27T15:42:58.532Z", "user": 1, "content_type": 8, "object_id": "9", "object_repr": "╨шрээр", "action_flag": 2, "change_message": "[{\"changed\": {\"fields\": [\"\\u041f\\u0443\\u0431\\u043b\\u0438\\u043a\\u0430\\u0446\\u0438\\u044f\"]}}]"}}, {"model": "admin.logentry", "pk": 31, "fields": {"action_time": "2023-07-27T15:42:58.533Z", "user": 1, "content_type": 8, "object_id": "10", "object_repr": "╪ръшЁр", "action_flag": 2, "change_message": "[{\"changed\": {\"fields\": [\"\\u041f\\u0443\\u0431\\u043b\\u0438\\u043a\\u0430\\u0446\\u0438\\u044f\"]}}]"}}, {"model": "admin.logentry", "pk": 32, "fields": {"action_time": "2023-07-27T15:42:58.534Z", "user": 1, "content_type": 8, "object_id": "11", "object_repr": "└эрёЄрёш  ▌°ыш", "action_flag": 2, "change_message": "[{\"changed\": {\"fields\": [\"\\u041f\\u0443\\u0431\\u043b\\u0438\\u043a\\u0430\\u0446\\u0438\\u044f\"]}}]"}}, {"model": "admin.logentry", "pk": 33, "fields": {"action_time": "2023-08-15T14:43:37.965Z", "user": 1, "content_type": 4, "object_id": "2", "object_repr": "user1", "action_flag": 3, "change_message": ""}}, {"model": "admin.logentry", "pk": 34, "fields": {"action_time": "2023-08-15T14:43:37.996Z", "user": 1, "content_type": 4, "object_id": "3", "object_repr": "user2", "action_flag": 3, "change_message": ""}}, {"model": "admin.logentry", "pk": 35, "fields": {"action_time": "2023-08-15T14:43:38.007Z", "user": 1, "content_type": 4, "object_id": "4", "object_repr": "user3", "action_flag": 3, "change_message": ""}}, {"model": "auth.user", "pk": 1, "fields": {"password": "pbkdf2_sha256$600000$JPqhtudMd3siulnS9XZuiW$P37YI6af5WRXMAiEssJLXoOkhoUQpUGnZylvsWSRHlQ=", "last_login": "2023-08-15T13:25:51.003Z", "is_superuser": true, "username": "andrew", "first_name": "", "last_name": "", "email": "", "is_staff": true, "is_active": true, "date_joined": "2023-07-26T08:39:34.315Z", "groups": [], "user_permissions": []}}, {"model": "sessions.session", "pk": "v0kh3nmqpbz6onz96u65xw6rq3vlojal", "fields": {"session_data": ".eJxVjEEOwiAQRe_C2pDCAB1cuu8ZyHQAqRqalHZlvLtt0oVu_3vvv0WgbS1ha2kJUxRXocTldxuJn6keID6o3mfJc12XaZSHIk_a5DDH9Lqd7t9BoVb22lrlmDsAcKzy3llgg4yZrPcps6aE4MH3KhuL6HRmb8hop7hH0yXx-QLfcTeH:1qVu3T:5kl3M2rb2pfJ5FFK6MnzmeZYFHSWxPJIBELzmzXiWZI", "expire_date": "2023-08-29T13:25:51.050Z"}}, {"model": "captcha.captchastore", "pk": 1, "fields": {"challenge": "NXQI", "response": "nxqi", "hashkey": "ad2775e1b08cc22f9bd3940ac1ac986fa535150e", "expiration": "2023-08-14T11:30:57.725Z"}}, {"model": "captcha.captchastore", "pk": 2, "fields": {"challenge": "LEEC", "response": "leec", "hashkey": "1b674cf583ebb7bf15259f2dab09f6a750eb782b", "expiration": "2023-08-14T12:34:15.465Z"}}, {"model": "captcha.captchastore", "pk": 3, "fields": {"challenge": "UZUV", "response": "uzuv", "hashkey": "16e35d6ecf2d9aa17076513d2b71e4308680179b", "expiration": "2023-08-14T12:35:53.876Z"}}, {"model": "captcha.captchastore", "pk": 4, "fields": {"challenge": "KIXF", "response": "kixf", "hashkey": "839c70046eba37ff087d22275aea68759a2ec7ab", "expiration": "2023-08-14T12:35:59.840Z"}}, {"model": "captcha.captchastore", "pk": 5, "fields": {"challenge": "WKHK", "response": "wkhk", "hashkey": "c3ff6d0c004c413b30bb143e8fd9311274a4221f", "expiration": "2023-08-14T12:36:13.187Z"}}, {"model": "captcha.captchastore", "pk": 6, "fields": {"challenge": "AHOU", "response": "ahou", "hashkey": "47a6a060235700ce266567f4c78bb12b81b1d134", "expiration": "2023-08-15T12:30:09.373Z"}}, {"model": "captcha.captchastore", "pk": 7, "fields": {"challenge": "YRRN", "response": "yrrn", "hashkey": "f7408b45af216d75256ed3e446af89beb4146411", "expiration": "2023-08-15T12:30:10.682Z"}}, {"model": "captcha.captchastore", "pk": 8, "fields": {"challenge": "DVPW", "response": "dvpw", "hashkey": "587653e7365610bf98a61d60a84ce720f6ab97d3", "expiration": "2023-08-15T12:30:14.900Z"}}, {"model": "captcha.captchastore", "pk": 9, "fields": {"challenge": "VWQK", "response": "vwqk", "hashkey": "0b0fb67a0314aabb170ca2b4d73310a7d5c6bf14", "expiration": "2023-08-15T12:30:17.323Z"}}, {"model": "captcha.captchastore", "pk": 10, "fields": {"challenge": "VABS", "response": "vabs", "hashkey": "07f354a462bb580dd2c903c3e4395ad8b863080b", "expiration": "2023-08-15T12:32:57.055Z"}}, {"model": "captcha.captchastore", "pk": 11, "fields": {"challenge": "AIXM", "response": "aixm", "hashkey": "db8170c99219f61aa2804392c3e5db9001d2f7b2", "expiration": "2023-08-15T12:33:00.273Z"}}, {"model": "captcha.captchastore", "pk": 12, "fields": {"challenge": "UZHF", "response": "uzhf", "hashkey": "d269dd58e60580dfb0d9be7d5cdf3e2dac072970", "expiration": "2023-08-15T12:38:17.640Z"}}, {"model": "captcha.captchastore", "pk": 13, "fields": {"challenge": "DZKK", "response": "dzkk", "hashkey": "40cc6e56da4eacd001510eb826350c683e12577d", "expiration": "2023-08-15T12:38:20.246Z"}}, {"model": "captcha.captchastore", "pk": 14, "fields": {"challenge": "BIOI", "response": "bioi", "hashkey": "ac9df882cc72ea87d1cec97c41a639cb17995cd0", "expiration": "2023-08-15T12:38:21.372Z"}}, {"model": "captcha.captchastore", "pk": 15, "fields": {"challenge": "GTSD", "response": "gtsd", "hashkey": "87011cb8219267a3d436c24b83d926eb33df9c4e", "expiration": "2023-08-15T12:38:31.298Z"}}, {"model": "captcha.captchastore", "pk": 16, "fields": {"challenge": "COAH", "response": "coah", "hashkey": "a6f6fa0c8493c4b80c2ad7b9d070f7c686c438db", "expiration": "2023-08-15T12:38:32.030Z"}}, {"model": "captcha.captchastore", "pk": 17, "fields": {"challenge": "NBOS", "response": "nbos", "hashkey": "340f810755b312368645bdcaedb848975687a8f2", "expiration": "2023-08-15T12:41:03.514Z"}}, {"model": "captcha.captchastore", "pk": 18, "fields": {"challenge": "BAOU", "response": "baou", "hashkey": "e19395cbc38e27148ee364e44f40c15f7e90a416", "expiration": "2023-08-15T12:42:55.092Z"}}, {"model": "captcha.captchastore", "pk": 19, "fields": {"challenge": "TYCG", "response": "tycg", "hashkey": "1e837f4c268d8d77267f5e5fea0279bfeddc07b1", "expiration": "2023-08-15T12:43:03.498Z"}}, {"model": "captcha.captchastore", "pk": 20, "fields": {"challenge": "MLLD", "response": "mlld", "hashkey": "529640b48264dab5077c2cbef07baeb87afddc38", "expiration": "2023-08-15T13:00:38.598Z"}}, {"model": "captcha.captchastore", "pk": 21, "fields": {"challenge": "PEYJ", "response": "peyj", "hashkey": "52c8744cbe79d4ada1ec42321d0108d792ee268f", "expiration": "2023-08-15T13:26:37.626Z"}}, {"model": "captcha.captchastore", "pk": 22, "fields": {"challenge": "USJG", "response": "usjg", "hashkey": "4f13923ae8b0df7f9dd4e3498adae5d3e510861a", "expiration": "2023-08-15T13:26:41.144Z"}}, {"model": "captcha.captchastore", "pk": 23, "fields": {"challenge": "JXQJ", "response": "jxqj", "hashkey": "f0d8fa5cf111c72fb67a4ff087d572f464b6df9a", "expiration": "2023-08-15T13:26:43.831Z"}}, {"model": "captcha.captchastore", "pk": 24, "fields": {"challenge": "FXKR", "response": "fxkr", "hashkey": "821082bbbafbff18cccb47965b391ad58f97641a", "expiration": "2023-08-15T13:26:47.773Z"}}, {"model": "captcha.captchastore", "pk": 25, "fields": {"challenge": "RWVJ", "response": "rwvj", "hashkey": "cb7300a56cf6e7ebce1aadd1c230e018e712c85e", "expiration": "2023-08-15T13:27:13.573Z"}}, {"model": "captcha.captchastore", "pk": 26, "fields": {"challenge": "FKEA", "response": "fkea", "hashkey": "4385282284c34597fb8fe8b89db6f7fe502573ad", "expiration": "2023-08-15T13:27:38.612Z"}}, {"model": "captcha.captchastore", "pk": 27, "fields": {"challenge": "LLPM", "response": "llpm", "hashkey": "3c1068a8708ab87b951cd8152d1f7a60bc72c724", "expiration": "2023-08-15T13:27:44.154Z"}}, {"model": "captcha.captchastore", "pk": 28, "fields": {"challenge": "BBFU", "response": "bbfu", "hashkey": "cb684dd6e3b74d722e5e3f4d7f06ef3c84f18878", "expiration": "2023-08-15T13:27:56.194Z"}}, {"model": "captcha.captchastore", "pk": 29, "fields": {"challenge": "KNQH", "response": "knqh", "hashkey": "409fb1f15a67abda654d2755b3fe072dd78d6d85", "expiration": "2023-08-15T13:27:59.506Z"}}, {"model": "captcha.captchastore", "pk": 30, "fields": {"challenge": "SGWB", "response": "sgwb", "hashkey": "b219abdb95b2193e1e65138a9ee26291a9a4016c", "expiration": "2023-08-15T13:30:54.923Z"}}, {"model": "captcha.captchastore", "pk": 31, "fields": {"challenge": "WFWQ", "response": "wfwq", "hashkey": "cd4d7739ca4c08cdf77635de6768728e34944568", "expiration": "2023-08-15T13:59:13.981Z"}}, {"model": "captcha.captchastore", "pk": 32, "fields": {"challenge": "WCZF", "response": "wczf", "hashkey": "162e695e0cfcfcb66b6b47ed5cc57368df29d89d", "expiration": "2023-08-15T14:01:42.523Z"}}, {"model": "women.women", "pk": 1, "fields": {"title": "╙ьр ╥єЁьрэ", "slug": "uma-turman", "content": 
